nextcaptcha/__init__.py
nextcaptcha/next.py
nextcaptcha_python-1.1.0.dist-info/LICENSE
nextcaptcha_python-1.1.0.dist-info/METADATA
nextcaptcha_python-1.1.0.dist-info/WHEEL
nextcaptcha_python-1.1.0.dist-info/top_level.txt
nextcaptcha_python-1.1.0.dist-info/RECORD
