Metadata-Version: 2.1
Name: nextcaptcha-python
Version: 1.1.0
Summary: NextCaptcha Captcha Solving Service Api Wrapper for Python to solving recaptcha v2, v3,recapthcha moible,hcaptcha,funcaptcha
Home-page: https://github.com/nextcaptcha/nextcaptcha-python/
Author: nextcaptcha
Author-email: support@nextcaptcha.com
Classifier: Programming Language :: Python :: 3
Classifier: License :: OSI Approved :: MIT License
Classifier: Operating System :: OS Independent
Requires-Python: >=3.6
License-File: LICENSE
Requires-Dist: requests
